buzz_agent/__init__.py
buzz_agent/buzz_agent.py
buzz_agent/six.py
buzz_agent-1.2.4.data/scripts/run_buzz_agent.py
buzz_agent-1.2.4.dist-info/METADATA
buzz_agent-1.2.4.dist-info/WHEEL
buzz_agent-1.2.4.dist-info/top_level.txt
buzz_agent-1.2.4.dist-info/RECORD
