Metadata-Version: 2.1
Name: buzz-agent
Version: 1.2.4
Summary: agent for buzz system
Home-page: https://github.com/dantezhu/buzz
Author: dantezhu
Author-email: dantezhu <dantezhu@qq.com>
License: MIT
Project-URL: Homepage, https://github.com/dantezhu/buzz
Platform: any
Requires-Dist: requests
Requires-Dist: whisper
